{
  "bundle": {
    "js/main": {
        "scripts": [
            "vendor/bootstrap-3.3.6/js/bootstrap.js",
            "vendor/jQueryValidation-1.14.0/jquery.validate.js",
            "vendor/jQueryValidation-1.14.0/additional-methods.js",
            "js/fortress-jqueryvalidation-methods.js",
            "js/uf-jqueryvalidation-config.js",
            "js/uf-alerts.js",
            "js/uf-form.js"
        ],
        "options": {
            "result": {
                "type": {
                  "scripts": "plain"
                }
            }
        }
    },
    "js/pages/register" : {
        "scripts": [
            "js/pages/register.js"
        ],
        "options": {
            "result": {
                "type": {
                  "scripts": "plain"
                }
            }
        }
    },
    "css/main": {
        "styles": [
            "vendor/font-awesome-4.5.0/css/font-awesome.css",
            "vendor/bootstrap-3.3.6/css/bootstrap.css",
            "vendor/start-bootstrap/css/modern-business.css"
        ],
        "options": {
            "result": {
                "type": {
                  "styles": "plain"
                }
            }
        }
    }
  },
  "copy": [
    {
        "src": "images/**/*",
        "base": "."
    },
    {
        "src": "vendor/font-awesome-4.5.0/fonts/**/*",
        "base": "vendor/font-awesome-4.5.0/"
    }
  ]
}
